gcp_pal/__init__.py
gcp_pal/artifactregistry.py
gcp_pal/bigquery.py
gcp_pal/cloudfunctions.py
gcp_pal/cloudrun.py
gcp_pal/cloudscheduler.py
gcp_pal/config/__init__.py
gcp_pal/config/vars.py
gcp_pal/dataplex.py
gcp_pal/datastore.py
gcp_pal/firestore.py
gcp_pal/project.py
gcp_pal/pubsub.py
gcp_pal/pydocker.py
gcp_pal/pylogging.py
gcp_pal/request.py
gcp_pal/schema.py
gcp_pal/secretmanager.py
gcp_pal/storage/__init__.py
gcp_pal/storage/parquet.py
gcp_pal/storage/storage.py
gcp_pal/utils/__init__.py
gcp_pal/utils/client_handler.py
gcp_pal/utils/lazy_loader.py
gcp_pal/utils/module_handler.py
gcp_pal/utils/utils.py
gcp_pal-1.0.41.dist-info/METADATA
gcp_pal-1.0.41.dist-info/WHEEL
gcp_pal-1.0.41.dist-info/RECORD
