Metadata-Version: 2.1
Name: gcp-pal
Version: 1.0.41
Summary: Set of utilities for interacting with Google Cloud Platform
Home-page: https://github.com/VitaminB16/gcp-pal
License: MIT
Keywords: gcp,google cloud,google cloud python,gcp api,gcp python api
Author: VitaminB16
Author-email: artemiy.nosov@gmail.com
Requires-Python: >=3.10
Classifier: License :: OSI Approved :: MIT License
Classifier: Programming Language :: Python :: 3
Classifier: Programming Language :: Python :: 3.10
Classifier: Programming Language :: Python :: 3.11
Classifier: Programming Language :: Python :: 3.12
Provides-Extra: all
Provides-Extra: artifactregistry
Provides-Extra: auth-oauthlib
Provides-Extra: bigquery
Provides-Extra: cloudfunctions
Provides-Extra: cloudrun
Provides-Extra: cloudscheduler
Provides-Extra: dataplex
Provides-Extra: datastore
Provides-Extra: docker
Provides-Extra: firestore
Provides-Extra: logging
Provides-Extra: pandas-gbq
Provides-Extra: parquet
Provides-Extra: project
Provides-Extra: pubsub
Provides-Extra: pyarrow
Provides-Extra: request
Provides-Extra: schema
Provides-Extra: secretmanager
Provides-Extra: storage
Requires-Dist: docker (>=7.1.0) ; extra == "cloudrun" or extra == "docker" or extra == "all"
Requires-Dist: gcsfs (>=2024.6.1) ; extra == "cloudfunctions" or extra == "storage" or extra == "all"
Requires-Dist: google-auth (>=2.29.0)
Requires-Dist: google-auth-oauthlib (>=1.2.0) ; extra == "auth-oauthlib" or extra == "all"
Requires-Dist: google-cloud (>=0.34.0)
Requires-Dist: google-cloud-artifact-registry (>=1.11.3) ; extra == "artifactregistry" or extra == "all"
Requires-Dist: google-cloud-bigquery (>=3.20.1) ; extra == "bigquery" or extra == "schema" or extra == "all"
Requires-Dist: google-cloud-core (>=2.4.1)
Requires-Dist: google-cloud-dataplex (>=1.13.0) ; extra == "dataplex" or extra == "all"
Requires-Dist: google-cloud-datastore (>=2.19.0) ; extra == "datastore" or extra == "all"
Requires-Dist: google-cloud-firestore (>=2.16.0) ; extra == "firestore" or extra == "all"
Requires-Dist: google-cloud-functions (>=1.16.3) ; extra == "cloudfunctions" or extra == "all"
Requires-Dist: google-cloud-logging (>=3.10.0) ; extra == "logging" or extra == "all"
Requires-Dist: google-cloud-pubsub (>=2.21.1) ; extra == "pubsub" or extra == "all"
Requires-Dist: google-cloud-resource-manager (>=1.12.3) ; extra == "cloudfunctions" or extra == "project" or extra == "all"
Requires-Dist: google-cloud-run (>=0.10.5) ; extra == "cloudrun" or extra == "all"
Requires-Dist: google-cloud-scheduler (>=2.13.3) ; extra == "cloudscheduler" or extra == "all"
Requires-Dist: google-cloud-secret-manager (>=2.19.0) ; extra == "secretmanager" or extra == "all"
Requires-Dist: google-cloud-storage (>=2.16.0) ; extra == "storage" or extra == "parquet" or extra == "all"
Requires-Dist: pandas-gbq (>=0.22.0) ; extra == "pandas-gbq" or extra == "all"
Requires-Dist: pyarrow (>=15.0.2) ; extra == "schema" or extra == "parquet" or extra == "pyarrow" or extra == "all"
Requires-Dist: requests (>=2.32.0) ; extra == "request"
